PySearcher/PySearcher.py
PySearcher/__init__.py
PySearcher/search.py
PySearcher-1.7.2.post2.dist-info/LICENSE
PySearcher-1.7.2.post2.dist-info/METADATA
PySearcher-1.7.2.post2.dist-info/WHEEL
PySearcher-1.7.2.post2.dist-info/top_level.txt
PySearcher-1.7.2.post2.dist-info/RECORD
