Metadata-Version: 2.1
Name: PySearcher
Version: 1.7.2.post2
Summary: Python Search Engine
Home-page: https://github.com/Tyrone-Zhao/PySearcher
Author: Tyrone Zhao
Author-email: tyrone-zhao@qq.com
License: UNKNOWN
Project-URL: Blog, https://blog.csdn.net/weixin_41845533
Keywords: code search tools
Platform: UNKNOWN
Classifier: Development Status :: 5 - Production/Stable
Classifier: Intended Audience :: Developers
Classifier: Topic :: Software Development :: Code Generators
Classifier: License :: OSI Approved :: MIT License
Classifier: Programming Language :: Python :: 3
Classifier: Programming Language :: Python :: 3.1
Classifier: Programming Language :: Python :: 3.2
Classifier: Programming Language :: Python :: 3.3
Classifier: Programming Language :: Python :: 3.4
Classifier: Programming Language :: Python :: 3.5
Classifier: Programming Language :: Python :: 3.6
Classifier: Programming Language :: Python :: 3.7
